AmazonParser/__init__.py
AmazonParser/bestsellers.py
AmazonParser/parser.py
AmazonParser-0.1.5.dist-info/METADATA
AmazonParser-0.1.5.dist-info/WHEEL
AmazonParser-0.1.5.dist-info/entry_points.txt
AmazonParser-0.1.5.dist-info/top_level.txt
AmazonParser-0.1.5.dist-info/RECORD
