Metadata-Version: 2.2
Name: AmazonParser
Version: 0.1.5
Summary: A Parser for Amazon Pages
Home-page: https://github.com/a4fr/AmazonParser
Author: Ali Najafi
Author-email: mail.ali.najafi@gmail.com
Classifier: Programming Language :: Python :: 3
Classifier: License :: OSI Approved :: MIT License
Classifier: Operating System :: OS Independent
Requires-Python: >=3.6
Requires-Dist: lxml
Dynamic: author
Dynamic: author-email
Dynamic: classifier
Dynamic: description
Dynamic: description-content-type
Dynamic: home-page
Dynamic: requires-dist
Dynamic: requires-python
Dynamic: summary
